{"client":"Thunder Client","collectionName":"flyweis","dateExported":"2022-03-03T15:22:51.629Z","version":"1.1","folders":[],"requests":[{"containerId":"","sortNum":10000,"headers":[{"name":"Accept","value":"*/*"},{"name":"User-Agent","value":"Thunder Client (https://www.thunderclient.com)"}],"colId":"a7bd3034-780d-4f90-8160-4ddba06ff4a0","name":"/login","url":"https://flyweis-interview.herokuapp.com/auth/login","method":"POST","modified":"2022-03-03T15:16:53.880Z","created":"2022-03-03T12:58:51.857Z","_id":"f902f7fe-47f1-4af4-8196-d9816cf46a6d","params":[],"body":{"type":"json","raw":"{\n    \"email\": \"web@test.com\",\n    \"password\": \"abcdefghi\"\n}","form":[]},"tests":[]},{"containerId":"","sortNum":20000,"headers":[{"name":"Accept","value":"*/*"},{"name":"User-Agent","value":"Thunder Client (https://www.thunderclient.com)"}],"colId":"a7bd3034-780d-4f90-8160-4ddba06ff4a0","name":"/forgot-password","url":"https://flyweis-interview.herokuapp.com/auth/forgot-password","method":"POST","modified":"2022-03-03T15:21:04.151Z","created":"2022-03-03T13:02:00.114Z","_id":"4bd05ba6-a269-497c-98c0-d770f6b6c105","params":[],"body":{"type":"json","raw":"{\n    \"email\": \"alpha@gmail.com\"\n}","form":[]},"auth":{"type":"bearer","bearer":"eyJhbGciOiJIUzI1NiIsInR5cCI6IkpXVCJ9.eyJfaWQiOiI2MjIwZDdlYjdjOWU0OTk2ZWU2ODMxMjgiLCJpYXQiOjE2NDYzMjA2MTN9.sK274T1RmSxkNxBfcE4iwK_S73fpLcKMMdZnEkNFt0M"},"tests":[]},{"containerId":"","sortNum":40000,"headers":[{"name":"Accept","value":"*/*"},{"name":"User-Agent","value":"Thunder Client (https://www.thunderclient.com)"}],"colId":"a7bd3034-780d-4f90-8160-4ddba06ff4a0","name":"/verify-otp","url":"https://flyweis-interview.herokuapp.com/auth/verify-otp","method":"POST","modified":"2022-03-03T15:19:01.784Z","created":"2022-03-03T13:04:42.106Z","_id":"66dceddc-f6a9-4bd8-a5c8-dec096530ca3","params":[],"body":{"type":"json","raw":"{\n    \"email\": \"alpha@gmail.com\",\n    \"otp\": 1234\n}","form":[]},"tests":[]},{"containerId":"","sortNum":60000,"headers":[{"name":"Accept","value":"*/*"},{"name":"User-Agent","value":"Thunder Client (https://www.thunderclient.com)"}],"colId":"a7bd3034-780d-4f90-8160-4ddba06ff4a0","name":"/all-courses","url":"https://flyweis-interview.herokuapp.com/courses/all-courses","method":"GET","modified":"2022-03-03T15:19:26.873Z","created":"2022-03-03T13:36:01.217Z","_id":"1f2d279c-e0f9-45b6-8ecc-29bc91dc709f","params":[],"tests":[]},{"containerId":"","sortNum":70000,"headers":[{"name":"Accept","value":"*/*"},{"name":"User-Agent","value":"Thunder Client (https://www.thunderclient.com)"}],"colId":"a7bd3034-780d-4f90-8160-4ddba06ff4a0","name":"/enroll","url":"https://flyweis-interview.herokuapp.com/courses/enroll","method":"POST","modified":"2022-03-03T15:20:17.663Z","created":"2022-03-03T13:44:57.450Z","_id":"33c02eb6-207c-4e25-a0fd-5e95f61dad38","params":[],"body":{"type":"json","raw":"{\n    \"email\": \"alpha@gmail.com\",\n    \"courseId\": 1234\n}","form":[]},"auth":{"type":"bearer","bearer":"eyJhbGciOiJIUzI1NiIsInR5cCI6IkpXVCJ9.eyJfaWQiOiI2MjIwZDdlYjdjOWU0OTk2ZWU2ODMxMjgiLCJpYXQiOjE2NDYzMjA2MTN9.sK274T1RmSxkNxBfcE4iwK_S73fpLcKMMdZnEkNFt0M"},"tests":[]},{"containerId":"","sortNum":80000,"headers":[{"name":"Accept","value":"*/*"},{"name":"User-Agent","value":"Thunder Client (https://www.thunderclient.com)"}],"colId":"a7bd3034-780d-4f90-8160-4ddba06ff4a0","name":"/create-dummy-course","url":"localhost:5000/courses/create-dummy-course","method":"GET","modified":"2022-03-03T14:27:32.771Z","created":"2022-03-03T14:26:30.839Z","_id":"d5dd8795-45e7-4788-9c48-a7fa80061dbe","params":[],"tests":[]},{"containerId":"","sortNum":90000,"headers":[{"name":"Accept","value":"*/*"},{"name":"User-Agent","value":"Thunder Client (https://www.thunderclient.com)"}],"colId":"a7bd3034-780d-4f90-8160-4ddba06ff4a0","name":"/signup","url":"https://flyweis-interview.herokuapp.com/auth/signup","method":"POST","modified":"2022-03-03T15:17:52.761Z","created":"2022-03-03T14:55:23.726Z","_id":"e6fcc1dd-848e-472e-8dc6-1de82ccb0eec","params":[],"body":{"type":"json","raw":"{\n    \"email\": \"web2@test.com\",\n    \"password\": \"abcdefghi\",\n    \"name\": \"Test2\"\n}","form":[]},"tests":[]},{"containerId":"","sortNum":100000,"headers":[{"name":"Accept","value":"*/*"},{"name":"User-Agent","value":"Thunder Client (https://www.thunderclient.com)"}],"colId":"a7bd3034-780d-4f90-8160-4ddba06ff4a0","name":"/logout","url":"https://flyweis-interview.herokuapp.com/auth/logout","method":"POST","modified":"2022-03-03T15:22:00.162Z","created":"2022-03-03T15:00:38.574Z","_id":"e46d4afa-e351-4a18-bfc6-e92d01a056e2","params":[],"auth":{"type":"bearer","bearer":"eyJhbGciOiJIUzI1NiIsInR5cCI6IkpXVCJ9.eyJfaWQiOiI2MjIwZDdlYjdjOWU0OTk2ZWU2ODMxMjgiLCJpYXQiOjE2NDYzMjA2MTN9.sK274T1RmSxkNxBfcE4iwK_S73fpLcKMMdZnEkNFt0M"},"tests":[]}]}
